test/__init__.py
unixgpt/__init__.py
unixgpt/__main__.py
unixgpt/argparser.py
unixgpt/cli.py
unixgpt/constants.py
unixgpt/errors.py
unixgpt/library.py
unixgpt/printer.py
unixgpt/prompts.py
unixgpt/utils.py
unixgpt/models/__init__.py
unixgpt/models/openai.py
unixgpt/models/training.py
unixgpt-0.1.6.dist-info/LICENSE
unixgpt-0.1.6.dist-info/METADATA
unixgpt-0.1.6.dist-info/WHEEL
unixgpt-0.1.6.dist-info/entry_points.txt
unixgpt-0.1.6.dist-info/top_level.txt
unixgpt-0.1.6.dist-info/RECORD
