Metadata-Version: 2.1
Name: unixgpt
Version: 0.1.6
Summary: unixgpt is a powerful bridge between natural language and UNIX commands
License: MIT
Classifier: Programming Language :: Python :: 3.8
Classifier: Programming Language :: Python :: 3.9
Classifier: Programming Language :: Python :: 3.10
License-File: LICENSE
Requires-Dist: openai ==0.28.1
Requires-Dist: pyperclip ==1.8.2
Requires-Dist: rich ==13.6.0
